{
  "maia-1900-predictions": {
    "h5h6": 0.3503,
    "h5f3": 0.1461,
    "h5e2": 0.0934,
    "h5g4": 0.0908,
    "d4d5": 0.0838,
    "e3h6": 0.0389,
    "b5d6": 0.0238,
    "h5d1": 0.0237,
    "a1b1": 0.0213,
    "h3f4": 0.0198,
    "f1f3": 0.0104,
    "c2g6": 0.0098,
    "h5h7": 0.0087,
    "c2e4": 0.007,
    "d4c5": 0.0069,
    "e3c1": 0.0045,
    "f1f6": 0.0044,
    "h3g5": 0.0038,
    "a1e1": 0.0037,
    "f1f7": 0.0036,
    "h5h4": 0.0035,
    "h3f2": 0.0034,
    "c2b3": 0.0033,
    "g1h1": 0.003,
    "f1f2": 0.0029,
    "h5f5": 0.0025,
    "a2a4": 0.0024,
    "b5a3": 0.0023,
    "h5g6": 0.0023,
    "c2d1": 0.002,
    "f1b1": 0.002,
    "e3d2": 0.0014,
    "b5a7": 0.0013,
    "e3f2": 0.0013,
    "c3c4": 0.0012,
    "g2g4": 0.0012,
    "a1c1": 0.0011,
    "b5c7": 0.0009,
    "f1f5": 0.0009,
    "e3g5": 0.0008,
    "a1d1": 0.0007,
    "h5g5": 0.0007,
    "a2a3": 0.0006,
    "f1f4": 0.0006,
    "e3f4": 0.0005,
    "g2g3": 0.0005,
    "c2b1": 0.0004,
    "c2a4": 0.0003,
    "c2f5": 0.0003,
    "f1c1": 0.0003,
    "c2d3": 0.0002,
    "f1e1": 0.0002,
    "f1d1": 0.0001,
    "g1f2": 0.0
  },
  "maia-1100-predictions": {
    "h5h6": 0.1874,
    "h5f3": 0.1589,
    "h5g4": 0.1238,
    "h5e2": 0.0913,
    "e3h6": 0.0768,
    "h3g5": 0.0576,
    "a1b1": 0.0392,
    "c2g6": 0.034,
    "d4d5": 0.0318,
    "h3f4": 0.0241,
    "h5d1": 0.0167,
    "d4c5": 0.0156,
    "h5h4": 0.0155,
    "b5d6": 0.0114,
    "e3c1": 0.0098,
    "e3g5": 0.0091,
    "f1f3": 0.0082,
    "b5a3": 0.0069,
    "c2d1": 0.0065,
    "a1e1": 0.0056,
    "f1f6": 0.0053,
    "c2b3": 0.0051,
    "f1b1": 0.0043,
    "f1f7": 0.0043,
    "h3f2": 0.0038,
    "h5h7": 0.0037,
    "h5g5": 0.0036,
    "c2e4": 0.0034,
    "f1f2": 0.0031,
    "h5f5": 0.0029,
    "a2a4": 0.0028,
    "h5g6": 0.0027,
    "a1c1": 0.0023,
    "g2g4": 0.0022,
    "e3d2": 0.0021,
    "g2g3": 0.0016,
    "c2b1": 0.0015,
    "e3f4": 0.0015,
    "e3f2": 0.0014,
    "c3c4": 0.0013,
    "g1h1": 0.0012,
    "a1d1": 0.0011,
    "a2a3": 0.0011,
    "b5c7": 0.001,
    "c2f5": 0.001,
    "c2a4": 0.0009,
    "c2d3": 0.0009,
    "f1f5": 0.0009,
    "f1f4": 0.0008,
    "f1e1": 0.0007,
    "b5a7": 0.0006,
    "f1c1": 0.0003,
    "g1f2": 0.0003,
    "f1d1": 0.0002
  }
}
